{
  "monsters": [
    {
      "id": "slime",
      "name": "Slime",
      "hp": 40,
      "str": 3,
      "def": 0,
      "agi": 2,
      "xp": 8,
      "aggroRange": 4,
      "attackRange": 1.2,
      "speed": 1.5,
      "modelPlaceholder": "#44cc44",
      "drops": [
        { "itemId": "pocao-pequena", "chance": 0.30 },
        { "itemId": "ouro", "chance": 0.80, "qty": { "min": 1, "max": 5 } }
      ],
      "soundProfile": {}
    },
    {
      "id": "goblin",
      "name": "Goblin",
      "hp": 65,
      "str": 6,
      "def": 1,
      "agi": 4,
      "xp": 18,
      "aggroRange": 5,
      "attackRange": 1.4,
      "speed": 2.5,
      "modelPlaceholder": "#88aa22",
      "drops": [
        { "itemId": "pocao-pequena", "chance": 0.20 },
        { "itemId": "adaga-iniciante", "chance": 0.05 },
        { "itemId": "ouro", "chance": 0.90, "qty": { "min": 3, "max": 10 } }
      ],
      "soundProfile": {}
    },
    {
      "id": "lobo",
      "name": "Lobo",
      "hp": 90,
      "str": 9,
      "def": 2,
      "agi": 6,
      "xp": 30,
      "aggroRange": 6,
      "attackRange": 1.3,
      "speed": 3.5,
      "modelPlaceholder": "#886644",
      "drops": [
        { "itemId": "pocao-pequena", "chance": 0.25 },
        { "itemId": "ouro", "chance": 0.85, "qty": { "min": 5, "max": 15 } }
      ],
      "soundProfile": {}
    },
    {
      "id": "besouro",
      "name": "Besouro",
      "hp": 110,
      "str": 8,
      "def": 5,
      "agi": 2,
      "xp": 35,
      "aggroRange": 3,
      "attackRange": 1.2,
      "speed": 1.8,
      "modelPlaceholder": "#224488",
      "drops": [
        { "itemId": "pocao-pequena", "chance": 0.15 },
        { "itemId": "armadura-cloth", "chance": 0.08 },
        { "itemId": "ouro", "chance": 0.70, "qty": { "min": 8, "max": 20 } }
      ],
      "soundProfile": {}
    },
    {
      "id": "esqueleto",
      "name": "Esqueleto",
      "hp": 130,
      "str": 12,
      "def": 3,
      "agi": 5,
      "xp": 55,
      "aggroRange": 5,
      "attackRange": 1.5,
      "speed": 2.8,
      "modelPlaceholder": "#ddddcc",
      "drops": [
        { "itemId": "pocao-azul", "chance": 0.20 },
        { "itemId": "espada-iniciante", "chance": 0.10 },
        { "itemId": "ouro", "chance": 0.90, "qty": { "min": 10, "max": 25 } }
      ],
      "soundProfile": {}
    },
    {
      "id": "golem-pequeno",
      "name": "Golem Pequeno",
      "hp": 200,
      "str": 15,
      "def": 10,
      "agi": 1,
      "xp": 80,
      "aggroRange": 3,
      "attackRange": 1.6,
      "speed": 1.2,
      "modelPlaceholder": "#888888",
      "drops": [
        { "itemId": "armadura-cloth", "chance": 0.30 },
        { "itemId": "ouro", "chance": 1.00, "qty": { "min": 15, "max": 30 } }
      ],
      "soundProfile": {}
    },
    {
      "id": "fada-corrompida",
      "name": "Fada Corrompida",
      "hp": 95,
      "str": 18,
      "def": 1,
      "agi": 8,
      "xp": 90,
      "aggroRange": 7,
      "attackRange": 2.5,
      "speed": 4.0,
      "modelPlaceholder": "#cc44cc",
      "drops": [
        { "itemId": "pocao-azul", "chance": 0.40 },
        { "itemId": "ouro", "chance": 0.95, "qty": { "min": 20, "max": 40 } }
      ],
      "soundProfile": {}
    },
    {
      "id": "lobisomem",
      "name": "Lobisomem",
      "hp": 320,
      "str": 25,
      "def": 8,
      "agi": 9,
      "xp": 180,
      "aggroRange": 8,
      "attackRange": 1.8,
      "speed": 4.5,
      "modelPlaceholder": "#553322",
      "drops": [
        { "itemId": "espada-iniciante", "chance": 0.25 },
        { "itemId": "machado-iniciante", "chance": 0.25 },
        { "itemId": "ouro", "chance": 1.00, "qty": { "min": 50, "max": 100 } }
      ],
      "soundProfile": {}
    }
  ]
}